odoo/addons/partner_bank_acc_type_constraint/README.rst
odoo/addons/partner_bank_acc_type_constraint/__init__.py
odoo/addons/partner_bank_acc_type_constraint/__manifest__.py
odoo/addons/partner_bank_acc_type_constraint/post_install.py
odoo/addons/partner_bank_acc_type_constraint/i18n/es.po
odoo/addons/partner_bank_acc_type_constraint/i18n/fr.po
odoo/addons/partner_bank_acc_type_constraint/i18n/partner_bank_acc_type_constraint.pot
odoo/addons/partner_bank_acc_type_constraint/models/__init__.py
odoo/addons/partner_bank_acc_type_constraint/models/res_partner_bank.py
odoo/addons/partner_bank_acc_type_constraint/readme/CONTRIBUTORS.rst
odoo/addons/partner_bank_acc_type_constraint/readme/DESCRIPTION.rst
odoo/addons/partner_bank_acc_type_constraint/static/description/icon.png
odoo/addons/partner_bank_acc_type_constraint/static/description/index.html
odoo/addons/partner_bank_acc_type_constraint/static/description/partner_bank_acc_type_raise.png
odoo/addons/partner_bank_acc_type_constraint/views/res_partner.xml
odoo/addons/partner_bank_acc_type_constraint/views/res_partner_bank.xml
odoo14_addon_partner_bank_acc_type_constraint-14.0.1.0.1.dev4.dist-info/METADATA
odoo14_addon_partner_bank_acc_type_constraint-14.0.1.0.1.dev4.dist-info/WHEEL
odoo14_addon_partner_bank_acc_type_constraint-14.0.1.0.1.dev4.dist-info/top_level.txt
odoo14_addon_partner_bank_acc_type_constraint-14.0.1.0.1.dev4.dist-info/RECORD
